hello_pypi_apacph/__init__.py
hello_pypi_apacph/calc.py
hello_pypi_apacph/dt.py
hello_pypi_apacph-0.1.0.dist-info/LICENSE
hello_pypi_apacph-0.1.0.dist-info/METADATA
hello_pypi_apacph-0.1.0.dist-info/WHEEL
hello_pypi_apacph-0.1.0.dist-info/top_level.txt
hello_pypi_apacph-0.1.0.dist-info/RECORD
