Metadata-Version: 2.1
Name: hello-pypi-apacph
Version: 0.1.0
Summary: A small example package
Author-email: Po-Hsun Cheng <apacph@gmail.com>
License: MIT License
Project-URL: Homepage, https://gitlab.com/apacph/hello_pypi_apacph
Project-URL: Issues, https://gitlab.com/apacph/hello_pypi_apacph/issues
Classifier: Programming Language :: Python :: 3
Classifier: License :: OSI Approved :: MIT License
Classifier: Operating System :: OS Independent
Requires-Python: >=3.8
License-File: LICENSE
